image_lister.py
image_lister-0.1.2.dist-info/DESCRIPTION.rst
image_lister-0.1.2.dist-info/WHEEL
image_lister-0.1.2.dist-info/metadata.json
image_lister-0.1.2.dist-info/entry_points.txt
image_lister-0.1.2.dist-info/RECORD
image_lister-0.1.2.dist-info/top_level.txt
image_lister-0.1.2.dist-info/METADATA
